arez/__init__.py
arez/api.py
arez/bounty.py
arez/cache.py
arez/champion.py
arez/endpoint.py
arez/enumerations.py
arez/enums.py
arez/exceptions.py
arez/items.py
arez/match.py
arez/mixins.py
arez/player.py
arez/py.typed
arez/responses.py
arez/stats.py
arez/status.py
arez/statuspage.py
arez/utils.py
aRez-0.2.4.dist-info/LICENSE
aRez-0.2.4.dist-info/METADATA
aRez-0.2.4.dist-info/WHEEL
aRez-0.2.4.dist-info/top_level.txt
aRez-0.2.4.dist-info/RECORD
