Metadata-Version: 2.1
Name: aRez
Version: 0.2.4
Summary: Async Python HiRez API wrapper
Home-page: https://github.com/DevilXD/aRez
Author: DevilXD
License: GPLv3
Project-URL: Source, https://github.com/DevilXD/aRez
Project-URL: Documentation, https://arez.readthedocs.io/en/latest/
Platform: UNKNOWN
Classifier: Development Status :: 3 - Alpha
Classifier: Framework :: AsyncIO
Classifier: Intended Audience :: Developers
Classifier: License :: OSI Approved :: GNU General Public License v3 (GPLv3)
Classifier: Natural Language :: English
Classifier: Operating System :: OS Independent
Classifier: Programming Language :: Python :: 3.8
Classifier: Topic :: Software Development :: Libraries :: Python Modules
Classifier: Typing :: Typed
Requires-Python: >=3.8
Requires-Dist: aiohttp (>=2.0)
